AUTHORS
COPYING-GPL-3
MANIFEST.in
README.md
VERSION
setup.cfg
setup.py
assets/kant.xml
assets/shoebot-ide.desktop
assets/shoebot-ide.jpg
assets/shoebot-ide.png
examples/COPYING
examples/animation/hypnoval.bot
examples/animation/parade.bot
examples/animation/patternfader.bot
examples/animation/wishyworm.bot
examples/basic/arc.bot
examples/basic/curveto.bot
examples/basic/keyboard.bot
examples/basic/mouse.bot
examples/basic/primitives.bot
examples/basic/random_circles.bot
examples/basic/shoebot.bot
examples/basic/transforms.bot
examples/demos/appending_transforms.bot
examples/demos/ariel.bot
examples/demos/blines_and_circloids.bot
examples/demos/blocks.bot
examples/demos/circles_and_beziers.bot
examples/demos/clock.bot
examples/demos/colorshader.bot
examples/demos/concentric_arrows.bot
examples/demos/covergen.bot
examples/demos/dendrite.bot
examples/demos/fireworks.bot
examples/demos/flowers.bot
examples/demos/life.bot
examples/demos/math_sculpture.bot
examples/demos/math_tunnel_effect.bot
examples/demos/nebula.bot
examples/demos/random-specimen.bot
examples/demos/star_fun.bot
examples/demos/sun_planet_moon.bot
examples/demos/tendrils.bot
examples/grid/balls.bot
examples/grid/color_grid.bot
examples/grid/foliage.bot
examples/grid/form_function.bot
examples/grid/nauseating.bot
examples/libraries/audio/70s_wallpaper.bot
examples/libraries/audio/README.md
examples/libraries/audio/reactive_cells.bot
examples/libraries/audio/requirements.txt
examples/libraries/audio/tunnel_graph.bot
examples/libraries/beziereditor/create_path.bot
examples/libraries/beziereditor/edit_path.bot
examples/libraries/beziereditor/path.svg
examples/libraries/beziereditor/path_import.bot
examples/libraries/boids/flytype.bot
examples/libraries/boids/swarm.bot
examples/libraries/color/colorlib_1.bot
examples/libraries/color/colorlib_2.bot
examples/libraries/color/gradient_list.bot
examples/libraries/color/hair.bot
examples/libraries/color/hair_shadow.bot
examples/libraries/color/rules.bot
shoebot.egg-info/PKG-INFO
shoebot.egg-info/SOURCES.txt
shoebot.egg-info/dependency_links.txt
shoebot.egg-info/entry_points.txt
shoebot.egg-info/requires.txt
shoebot.egg-info/top_level.txt
