Metadata-Version: 2.1
Name: shoebot
Version: 1.4.0
Summary: Vector graphics scripting application
Home-page: http://shoebot.net
Author: Ricardo Lafuente
Author-email: r@manufacturaindependente.org
License: GPL v3
Platform: UNKNOWN
License-File: COPYING-GPL-3
License-File: AUTHORS
